Workbook

Sheet Planilha1
A1: Grupo Pessoa | B1: e-mail
A2: 3B INDUSTRIA E COMERCIO LTDA | B2: sarah@3rsconfeccoes.com.br
A3: 3RS CONFECCOES LTDA | B3: sarah@3rsconfeccoes.com.br;charlene@3rsconfeccoes.com.br;danfe@3rsconfeccoes.com.br;contasapagar@3rsconfeccoes.com.br;charlene@floripatextil.com.br
A4: A RELA SA INDUSTRIA E COMERCIO | B4: eliete.catarina@gina.com.br
A5: ADIMIX INDUSTRIA E COMERCIO DE ADITIVOS PARA PANIFIC LT | B5: fiscal2@adimix.com.br;compras@adimix.com.br
A6: AGISTERELI COMERCIAL EIRELI | B6: mara@saggiodobrasil.com.br
A7: AKAZZO INDUSTRIA DE CALCADOS LTDA | B7: faturamento@akazzo.com.br
A8: ALCOFLAME IND COM PROD QUIM E MAQ LTDA | B8: jrenato@alcoflame.com.br
A9: ALE IND. MET. E PLASTICOS EIRELI | B9: faturamento@alegrete.net
A10: ALFAPET PRODUTOS PARA ANIMAIS LIMITADA | B10: adilson@alfapetgranulados.com.br
A11: ALIMENTOS TIA SONIA LTDA | B11: c.logistica@tiasonia.com.br;logistica4@tiasonia.com.br;logistica6@tiasonia.com.br
A12: AMENDO LOVERS INDUSTRIA E COMERCIO DE ALIMENTOS LTDA | B12: flavio.lellis@amendolovers.com.br;atendimento@amendolovers.com.br;anisio@amendolovers.com.br;marcia@amendolovers.com.br
... A274: VIVANT WINES INDUSTRIA E COMERCIO DE VINHOS SA | B274: andre@betterdrinks.com;nathalia.scott@vivantwines.com;paula@vivantwines.com;paula@vivantwines.com;carla.franca@vivantwines.com
A275: VKB ARTEFATOS DE LATEX LTDA
A276: VOLKMANN ALIMENTOS LTDA | B276: atendimento@volkmann.com.br
A277: VOLNEI DALCIN | B277: volneidalcin@gmail.com
A278: VOX INDUSTRIA E COMERCIO DE PLASTICOS EIRELI | B278: comercial@libertyplast.com.br;producao.ricardo@libertyplast.com.br;ADM@LIBERTYPLAST.COM.BR
A279: WEST GARDEN INDUSTRIA E COMERCIO LTDA | B279: elis.coelho@westgarden.com.br;financeiro@westgarden.com.br;nfe@westgarden.com.br;thais.alves@westgarden.com.br
A280: WORKSEG CONFECCOES E FERRAMENTAS LTDA
A281: Y.D. CONFECCOES LTDA | B281: marciorodrigues@callu.com.br

Sheet Planilha2
A1: Grupo Pessoa | B1: E-mail
A2: AMENDO LOVERS INDUSTRIA E COMERCIO DE ALIMENTOS LTDA | B2: =VLOOKUP(A2,Planilha1!A:B,2,0) -> flavio.lellis@amendolovers.com.br;atendimento@amendolovers.com.br;anisio@amendolovers.com.br;marcia@amendolovers.com.br
A3: ARTSANA BRASIL LTDA | B3: BR_Agendamentos@artsana.com>; leticia.lovato@artsana.com; Luiz.Costa@artsana.com>;
A4: EMCOMEX EMPRESA DE COMERCIO EXTERIOR LTDA | B4: =VLOOKUP(A4,Planilha1!A:B,2,0) -> apoiologistica2@buw.com.br;laianegabriel@buw.com.br;evandropazetto@buw.com.br
A5: BERBERT INDUSTRIA E COM DE ALI LTDA - EP | B5: =VLOOKUP(A5,Planilha1!A:B,2,0) -> biscoitofranbert@uol.com.br;juniorberbert@hotmail.com
A6: CONDOR S.A | B6: simone.santos@condor.ind.br; marlei.ganske@condor.ind.br
A7: SANTHER FABRICA DE P S T SA | B7: =VLOOKUP(A7,Planilha1!A:B,2,0) -> wendell.reis@santher.com.br;nfse@santher.com.br
A8: VIA VERNAGLIA MASSAS PREMIUM LTDA. | B8: pacheco.bemviver@gmail.com
A9: POLYPETRO IND E COM DE PLASTICOS LTDA | B9: gabriel@polypetro.com.br
A10: GSA GAMA SUCOS E ALIMENTOS LTDA. | B10: Sheila.Macedo@grupogsa.com.br; Marcelo.Souza@grupogsa.com.br; Wesley.Rodrigues@grupogsa.com.br
A11: ALIMENTOS TIA SONIA LTDA | B11: =VLOOKUP(A11,Planilha1!A:B,2,0) -> c.logistica@tiasonia.com.br;logistica4@tiasonia.com.br;logistica6@tiasonia.com.br
A12: INDUSTRIA DE TORRONE NOSSA SENHORA DE MONTEVERGINE LTDA | B12: =VLOOKUP(A12,Planilha1!A:B,2,0) -> transporte.mv@montevergine.com.br;edi.transporte@montevergine.com.br;valdelice.lopes@montevergine.com.br
A13: LIQUID BRANDS INDUSTRIA E COMERCIO | B13: =VLOOKUP(A13,Planilha1!A:B,2,0) -> financeiro@liquid.ind.br;thiago@liquid.ind.br
A14: BOMBRIL S.A | B14: camila.paiva@bombril.com.br; barbara.nicholli@bombril.com.br
A15: RECKITT BENCKISER (BRASIL) | B15: =VLOOKUP(A15,Planilha1!A:B,2,0) -> DocumentosNDD@rb.com
A16: ROCA PRONTA CONSERVAS E ANTEPASTOS EIRELI | B16: =VLOOKUP(A16,Planilha1!A:B,2,0) -> comercial@hortalica.com.br
A17: SUZANO S.A. | B17: =VLOOKUP(A17,Planilha1!A:B,2,0) -> nfs@suzano.com.br
A18: INGREDIENT INDUSTRIA E COMERCIO DE ALIMENTOS LTDA | B18: =VLOOKUP(A18,Planilha1!A:B,2,0) -> arnaldo@ingredient.com.br
A19: BARILLA DO BRASIL LTDA | B19: Helio.Canever@barilla.com; Adriano.Alves@barilla.com
A20: REAL COMERCIAL LTDA | B20: =VLOOKUP(A20,Planilha1!A:B,2,0) -> logistica@lapastina.com;jhonatan.beserra@grupolapastina.com.br;matheus.santos@grupolapastina.com.br;renato.perciani@grupolapastina.com.br
A21: A RELA SA INDUSTRIA E COMERCIO | B21: =VLOOKUP(A21,Planilha1!A:B,2,0) -> eliete.catarina@gina.com.br
A22: SOVENA BRASIL SERVICOS DE CONSULTORIA E COMERCIO DE ALIMENTO | B22: =VLOOKUP(A22,Planilha1!A:B,2,0) -> patricia.fernandes@sovena.com.br;accountspayable@sovena.com.br;andressa.passos@sovena.com.br;felipe.gevaerd@sovena.com.br;Alexander.lopes@sovena.com.br;rute.parreira@sovena.pt
A23: ALI-NUTRI INDUSTRIA, COMERCIO E IMPORTACAO LTDA | B23: vendas@alinutrialimentos.com.br
A24: PERFETTI VAN MELLE BRASIL LTDA. | B24: rogerio.cipriano@PerfettiVanMelle.com; rachel.castro@PerfettiVanMelle.com; sueli.souza@PerfettiVanMelle.com
A25: CRISTIANE NASCIMENTO PEREIRA ME | B25: =VLOOKUP(A25,Planilha1!A:B,2,0) -> matodoce@matodoce.com.br
A26: NILPAN IND E COM DE ADITIVOS E PRE MIST P/ PANIF LTDA | B26: faturamento@nilpan.com.br; jorge.cafe@nilpan.com.br; andre.meneses@nilpan.com.br
A27: PROCTER & GAMBLE INDUSTRIAL E COMERCIAL LTDA | B27: =VLOOKUP(A27,Planilha1!A:B,2,0) -> peg_nfe@nfe.ind.br;junior.o@pg.com
A28: AURORA BEBIDAS E ALIMENTOS FINOS LTDA | B28: bruna.arrais@aurora.com.br; anesio.junior@aurora.com.br
A29: MEGABRAYN DO BRASIL LTDA | B29: =VLOOKUP(A29,Planilha1!A:B,2,0) -> wallacy.souza@cafesantamonica.com.br;financeiro1@cafesantamonica.com.br;Logistica1@cafesantamonica.com.br;bispo@cafesantamonica.com.br
A30: SANAJ INDUSTRIAL LTDA | B30: dilene@sanaj.com.br; faturamento@sanaj.com.br
A31: MISASPEL COMERCIO DE PAPEIS LTDA
A32: MARCOS ART P PANIFICACAO LTDA | B32: =VLOOKUP(A32,Planilha1!A:B,2,0) -> ribeiropan2@gmail.com;recebimento@casadoconfeiteiro.com.br;grace.guin@casadoconfeiteiro.com.br;cr@casadoconfeiteiro.com.br
A33: BEG DESTILARIA COMERCIO E DISTRIBUICAO DE BEBIDAS- LTDA | B33: financeiro@beggin.com.br; aflosi@beggin.com.br
A34: BRG SUPLEMENTOS NUTRICIONAIS LTDA | B34: guilherme.lopes@integralmedica.com; ronei.santos@integralmedica.com
A35: INDUSTRIAS ANHEMBI LTDA | B35: stephanie.carneiro@anhembi.ind.br; gustavo.vianna@anhembi.ind.br
A36: MELHORAMENTOS PAPÉIS LTDA | B36: =VLOOKUP(A36,Planilha1!A:B,2,0) -> ahmata@softys.com
A37: TING INDUSTRIA E COMERCIO LTDA | B37: =VLOOKUP(A37,Planilha1!A:B,2,0) -> agendamento@ting.com.br
A38: COALA DO BRASIL LTDA | B38: auxlogistica@coala.com.br
A39: UTILITY HOUSE ARTEFATOS EMBALADOS LTDA | B39: =VLOOKUP(A39,Planilha1!A:B,2,0) -> faturamento@cicley.com.br
A40: GALAXY PARTICIPAÇÕES IMP E EXP LTDA | B40: milena.assis@galaxyled.com.br; logistica2@galaxyled.com.br;
A41: BRASIL ESPRESSO COMERCIO ATACADISTA LTDA | B41: =VLOOKUP(A41,Planilha1!A:B,2,0) -> edimar.oliveira@grancoffee.com.br
A42: LEGRAND BRASIL LTDA | B42: rafaela.miranda@legrand.com;
A43: NOTCO BRASIL DISTRIBUICAO E COMERCIO DE PRODUTOS ALIMENTICIOS LTDA. | B43: =VLOOKUP(A43,Planilha1!A:B,2,0) -> ricardo.brinchi@thenotcompany.com;willian.pardim@thenotcompany.com;micaela.fernandes@thenotcompany.com;financeiro.br@thenotcompany.com
A44: APG COMERCIO DE BRINDES LTDA | B44: =VLOOKUP(A44,Planilha1!A:B,2,0) -> vendas@pggraf.com.br
A45: CERAS JOHNSON LTDA | B45: =VLOOKUP(A45,Planilha1!A:B,2,0) -> ADasilv@scj.com;iparais@scj.com;MOlivei2@scj.com
A46: ENOVA FOODS S.A. | B46: =VLOOKUP(A46,Planilha1!A:B,2,0) -> eduardo.costa@enovafoods.com.br;gkofrete@enovafoods.com.br;admlogistica@enovafoods.com.br
A47: VERDECO IND COM E IMP DE ARTEFATOS PARA JARDIM LTDA
A48: VAPZA ALIMENTOS S/A | B48: =VLOOKUP(A48,Planilha1!A:B,2,0) -> fernanda.jesus@vapza.com.br
A49: VALE BRILHANTE IND E COM LTDA | B49: industrial@valebrilhante.com.br; jairo@valebrilhante.com.br
A50: SORA ALIMENTOS LTDA | B50: pacheco.bemviver@gmail.com; comercial@sundhed.com.br
A51: RICH DO BRASIL LTDA | B51: =VLOOKUP(A51,Planilha1!A:B,2,0) -> rsantos@rich.com
A52: INDUSTRIA DE PROD ALIMENTICIOS REZENDE LTDA | B52: comercial@maltaerezende.com.br;
A53: RB EXP IMP COM E IND DE PRODUTOS DE BARBEAR LTDA | B53: financeiro@rbprodutosdebarbear.com.br; administrativo@rbprodutosdebarbear.com.br
A54: PRO NOVA DISTRIBUIDORA E COMERCIO DE COSMETICOS LTDA | B54: paulo.monte@pronovacosmeticos.com.br; viviane.cruz@pronovacosmeticos.com.br
A55: MINAPLAST MAQUINAS INDUSTRIAIS E ARTEFATOS PLASTICOS LTDA | B55: logistica@minaplast.com.br; entregas@minaplast.com.br
A56: CASSINI ALIMENTOS LTDA | B56: pedido@cassini.com.br
A57: BR SPICES INDUSTRIA E COMERCIO DE ALIMENTOS EIRELI | B57: =VLOOKUP(A57,Planilha1!A:B,2,0) -> logistica5@brspices.com.br;adm@brspices.com.br;logistica@brspices.com.br;logistica2@brspices.com.br;logistica4@brspices.com.br;adm2@brspices.com.br
A58: BETTER DRINKS DIST. E ATAC. DE BEBIDAS S/A | B58: cris@betterdrinks.com; luany@betterdrinks.com
A59: BASTON INDUSTRIA DE AEROSSOIS LTDA | B59: bruna.quadros@baston.com.br; Agendamento@baston.com.br
A60: IND COM PROD ALIM CEPERA LTDA | B60: priscila.vidotto@cepera.com.br
A61: KELCO PET CARE PRODUTOS ANIMAIS LTDA | B61: =VLOOKUP(A61,Planilha1!A:B,2,0) -> mhrosa@bentonit.com.br
A62: COLAVITA BRASIL COMERCIAL IMP E EXP EIRELI | B62: colavita@colavita.com.br
A63: CRIA SIM PRODUTOS DE HIGIENE LTDA | B63: pbarroso@casakm.com.br; mfurtado@casakm.com.br
A64: RED BULL DO BRASIL LTDA. | B64: =VLOOKUP(A64,Planilha1!A:B,2,0) -> transporte01@fortelogistica.com.br;Ana.Oliveira2@redbull.com; fernanda.dias@fortelogistica.com.br;fernanda.dias@fortelogistica.com.br;Larissa.Santos@redbull.com
A65: M DIAS BRANCO S.A INDUSTRIA DE COM ALIME | B65: =VLOOKUP(A65,Planilha1!A:B,2,0) -> amorim.paula@mdiasbranco.com.br;leandro.avellar@mdiasbranco.com.br;agnaldo.silva@mdiasbranco.com.br;ricardo.accioly@mdiasbranco.com.br;kazuyuki.iriguchi@mdiasbranco.com.br
A66: ALCA FOODS LIMITADA | B66: murillo.oliveira@alcafoods.com; logistica@alcafoods.com
A67: METALURGICA MOR | B67: =VLOOKUP(A67,Planilha1!A:B,2,0) -> faturaslog@mor.com.br;cte@mordistribuidora.com.br;cte@mor.com.br;cargas02@mor.com.br;cargas03@mor.com.br
A68: INDUSTRIAS REUNIDAS RAYMUNDO DA FONTE SA | B68: marcio.gv@rfonte.com.br; erick.fa@rfonte.com.br
A69: KIMBERLY CLARK BRASIL IND COM PROD HIG LTDA | B69: =VLOOKUP(A69,Planilha1!A:B,2,0) -> Fabio.Kenji@kcc.com;lasantos@kcc.com;Edgar.Alves@kcc.com;Sadi.S.Oliveira@kcc.com
A70: SANTA LUCIA ALIMENTOS LTDA | B70: jlopes@blueville.com.br; bdalben@blueville.com.br; cviana@blueville.com.br
A71: ADIMIX INDUSTRIA E COMERCIO DE ADITIVOS PARA PANIFIC LT | B71: =VLOOKUP(A71,Planilha1!A:B,2,0) -> fiscal2@adimix.com.br;compras@adimix.com.br
A72: ALFAPET PRODUTOS PARA ANIMAIS LIMITADA | B72: =VLOOKUP(A72,Planilha1!A:B,2,0) -> adilson@alfapetgranulados.com.br
A73: AMERICAN PETS DO BRASIL LTDA | B73: =VLOOKUP(A73,Planilha1!A:B,2,0) -> marcelo@chalesco.com.br
A74: APG Uniformes Sociedade Unipessoal LTDA - ME | B74: adm@pggraf.com.br; vendas@pggraf.com.br
A75: CAMIL ALIMENTOS S.A. | B75: marcio.fernandes@camil.com.br; rudiney.bunde@camil.com.br; eliete.souza@camil.com.br
A76: CIA CANOINHAS DE PAPEL | B76: =VLOOKUP(A76,Planilha1!A:B,2,0) -> luciano.logistica@canoinhas.com.br;santin.cwb@canoinhas.com.br;Thaimara.logistica@canoinhas.com.br; juliana.financeiro@canoinhas.com.br
A77: CLESS COMERCIO DE COSMETICOS S.A. | B77: gcandido@akua.com.br; etugnette@akua.com.br
A78: COLGATE-PALMOLIVE COMERCIAL LTDA. | B78: =VLOOKUP(A78,Planilha1!A:B,2,0) -> cte_colgate@colpal.com;mario_mendoza@colpal.com;joao_pessoa@colpal.com
A79: COLUMBIA COMERCIO DE DESCARTAVEIS EIRELI | B79: marcia.rosa@columbiasupri.com.br;
A80: ELECTROLUX DO BRASIL S/A | B80: =VLOOKUP(A80,Planilha1!A:B,2,0) -> daniel.pachecoski@electrolux.com;jonathan.bubiniak@electrolux.com
A81: EMPORIO BLEND BRAZIL LTDA | B81: =VLOOKUP(A81,Planilha1!A:B,2,0) -> crp.luciana@gmail.com
A82: FLORIO PRODUTOS ALIMENTICIOS LTDA | B82: =VLOOKUP(A82,Planilha1!A:B,2,0) -> edna.cerqueira@florioalimentos.com.br
A83: GEORGE CRUM DO BRASIL LTDA | B83: =VLOOKUP(A83,Planilha1!A:B,2,0) -> comercial@mrcrums.com.br
A84: HASBRO DO BRASIL | B84: =VLOOKUP(A84,Planilha1!A:B,2,0) -> Andre.Fassini@hasbro.com;Andre.Souza@hasbro.com;Danilo.Ribeiro@hasbro.com
A85: HTR COMERCIO ATACADISTA DE ALIMENTOS LTDA. | B85: amarques@damagrinha.com.br; vendas@damagrinha.com.br
A86: HYGIELINE INDUSTRIA E COMERCIO LTDA | B86: =VLOOKUP(A86,Planilha1!A:B,2,0) -> expedicao@toallitas.com.br
A87: KAERPEN ALIMENTOS LTDA | B87: comercial.lebre@uol.com.br; financeiro@kaerpen.com.br
A88: MAZAL IMPORTACAO E EXPORTACAO DE ALIMENTOS LTDA | B88: =VLOOKUP(A88,Planilha1!A:B,2,0) -> HENRY@MAZALIMPORTS.COM.BR;Gabriel@mazalimports.com.br
A89: METRAPACK FILMES TECNICOS LTDA | B89: =VLOOKUP(A89,Planilha1!A:B,2,0) -> vendas@metrapack.com.br
A90: MULTILASER INDUSTRIAL S.A. | B90: =VLOOKUP(A90,Planilha1!A:B,2,0) -> agendamento03@multilaser.com.br
A91: NATIQUE INDUSTRIA E COMERCIO LTDA | B91: =VLOOKUP(A91,Planilha1!A:B,2,0) -> fsilva@natique.com.br
A92: PONZAN IND E COM PROD ALIM LTDA | B92: suporteestrategico@ponzan.com.br; logistica@ponzan.com.br
A93: PURATOS BRASIL LTDA | B93: LSiqueira@puratos.com;WAlmeidaDeOliveira@puratos.com
A94: SAKURA NAKAYA ALIMENTOS LTDA | B94: =VLOOKUP(A94,Planilha1!A:B,2,0) -> priscila.rodrigues@sakura.com.br
A95: SERT PLAST IND E COM LTDA | B95: rem_brant@terra.com.br;
A96: SOL PANAMBY SPECIALTY COFFEES LTDA. | B96: tatianadias@octaviocafe.com.br; lauralonardi@ocoffee.com.br; franclintavares@octaviocafe.com.br
A97: SUPREMO COMER ATAC DIST PROD PLAS EIRELI | B97: =VLOOKUP(A97,Planilha1!A:B,2,0) -> comercial@supersupremo.com.br;financeiro@supersupremo.com.br
A98: TOTAL QUIMICA LIMITADA | B98: marcos.macedo@sanol.com.br;
A99: TRENCH ALIMENTOS LTDA | B99: trench.alimentos@uol.com.br;
A100: VCT BRASIL IMPORTACAO E EXPORTACAO LTDA | B100: =VLOOKUP(A100,Planilha1!A:B,2,0) -> leandro.mendes@vctbrasil.com;ricardo.mendonca@vctbrasil.com
...
